{
    "version": {
        "major": 1,
        "minor": 0
    },
    "blocks": [
        {
            "type": "Heading",
            "level": 1,
            "contents": [
                {
                    "type": "Text",
                    "text": "some markdown"
                }
            ]
        },
        {
            "type": "Heading",
            "level": 3,
            "contents": [
                {
                    "type": "Text",
                    "text": "HTML Block"
                }
            ]
        },
        {
            "type": "Paragraph",
            "contents": [
                {
                    "type": "Text",
                    "text": "kjsdfkjhasd <p>Test<\/p> ksajdhfgkasjhfgd"
                }
            ]
        },
        {
            "type": "Heading",
            "level": 3,
            "contents": [
                {
                    "type": "Text",
                    "text": "blocks in a quote block"
                }
            ]
        }
    ]
}